neuronode/Debug.py
neuronode/__init__.py
NeuroNode-9.3.dist-info/LICENSE.text
NeuroNode-9.3.dist-info/METADATA
NeuroNode-9.3.dist-info/WHEEL
NeuroNode-9.3.dist-info/top_level.txt
NeuroNode-9.3.dist-info/RECORD
